getmail-6.19.10.data/data/share/doc/getmail/BUGS
getmail-6.19.10.data/data/share/doc/getmail/CHANGELOG
getmail-6.19.10.data/data/share/doc/getmail/COPYING
getmail-6.19.10.data/data/share/doc/getmail/README
getmail-6.19.10.data/data/share/doc/getmail/THANKS
getmail-6.19.10.data/data/share/doc/getmail/configuration.html
getmail-6.19.10.data/data/share/doc/getmail/configuration.txt
getmail-6.19.10.data/data/share/doc/getmail/documentation.html
getmail-6.19.10.data/data/share/doc/getmail/documentation.txt
getmail-6.19.10.data/data/share/doc/getmail/faq.html
getmail-6.19.10.data/data/share/doc/getmail/faq.txt
getmail-6.19.10.data/data/share/doc/getmail/getmaildocs.css
getmail-6.19.10.data/data/share/doc/getmail/getmailrc-examples
getmail-6.19.10.data/data/share/doc/getmail/troubleshooting.html
getmail-6.19.10.data/data/share/doc/getmail/troubleshooting.txt
getmail-6.19.10.data/data/share/man/man1/getmail.1
getmail-6.19.10.data/data/share/man/man1/getmail_fetch.1
getmail-6.19.10.data/data/share/man/man1/getmail_maildir.1
getmail-6.19.10.data/data/share/man/man1/getmail_mbox.1
getmail-6.19.10.data/data/share/man/man1/getmails.1
getmail-6.19.10.data/scripts/getmail
getmail-6.19.10.data/scripts/getmail-gmail-xoauth-tokens
getmail-6.19.10.data/scripts/getmail_fetch
getmail-6.19.10.data/scripts/getmail_maildir
getmail-6.19.10.data/scripts/getmail_mbox
getmail-6.19.10.data/scripts/getmails
getmailcore/__init__.py
getmailcore/_retrieverbases.py
getmailcore/baseclasses.py
getmailcore/constants.py
getmailcore/destinations.py
getmailcore/exceptions.py
getmailcore/filters.py
getmailcore/imap_utf7.py
getmailcore/logging.py
getmailcore/message.py
getmailcore/retrievers.py
getmailcore/utilities.py
getmail-6.19.10.dist-info/METADATA
getmail-6.19.10.dist-info/WHEEL
getmail-6.19.10.dist-info/top_level.txt
getmail-6.19.10.dist-info/RECORD
