Metadata-Version: 2.1
Name: getmail
Version: 6.19.10
Summary: a mail retrieval, sorting, and delivering system
Home-page: https://www.getmail6.org/
Download-URL: https://github.com/getmail6/getmail6/releases
Author: Charles Cazabon, Roland Puntaier, and others
Author-email: charlesc-getmail@pyropus.ca
Maintainer-email: roland.puntaier@gmail.com
License: GPL-2.0
Classifier: Development Status :: 4 - Beta
Classifier: Environment :: Console
Classifier: Intended Audience :: End Users/Desktop
Classifier: Intended Audience :: System Administrators
Classifier: License :: OSI Approved :: GNU General Public License (GPL)
Classifier: License :: OSI Approved :: Apache Software License
Classifier: Natural Language :: English
Classifier: Operating System :: OS Independent
Classifier: Operating System :: POSIX
Classifier: Programming Language :: Python
Classifier: Topic :: Communications :: Email
Classifier: Topic :: Communications :: Email :: Filters
Classifier: Topic :: Communications :: Email :: Post-Office :: IMAP
Classifier: Topic :: Communications :: Email :: Post-Office :: POP3
Classifier: Topic :: Software Development :: Libraries :: Python Modules
Classifier: Topic :: Utilities
